csvcubed/README.md
csvcubed/__init__.py
csvcubed/cli/__init__.py
csvcubed/cli/buildcsvw/__init__.py
csvcubed/cli/buildcsvw/build.py
csvcubed/cli/codelist/__init__.py
csvcubed/cli/codelist/build_code_list.py
csvcubed/cli/entrypoint.py
csvcubed/cli/error_mapping.py
csvcubed/cli/inspectcsvw/README.md
csvcubed/cli/inspectcsvw/__init__.py
csvcubed/cli/inspectcsvw/inspect.py
csvcubed/cli/inspectcsvw/metadatainputvalidator.py
csvcubed/cli/inspectcsvw/metadataprinter.py
csvcubed/cli/pullcsvw/__init__.py
csvcubed/cli/pullcsvw/pull.py
csvcubed/definitions.py
csvcubed/feature_flags.py
csvcubed/inputs.py
csvcubed/inspect/inspectdatasetmanager.py
csvcubed/inspect/inspectorcolumns.py
csvcubed/inspect/inspectorcomponents.py
csvcubed/inspect/inspectors.py
csvcubed/inspect/inspectortable.py
csvcubed/inspect/lazyfuncdescriptor.py
csvcubed/inspect/sparql_handler/__init__.py
csvcubed/inspect/sparql_handler/code_list_repository.py
csvcubed/inspect/sparql_handler/csvw_repository.py
csvcubed/inspect/sparql_handler/data_cube_repository.py
csvcubed/inspect/sparql_handler/sparql.py
csvcubed/inspect/sparql_handler/sparql_queries/ask_is_codelist.sparql
csvcubed/inspect/sparql_handler/sparql_queries/ask_is_qb_dataset.sparql
csvcubed/inspect/sparql_handler/sparql_queries/select_build_information.sparql
csvcubed/inspect/sparql_handler/sparql_queries/select_catalog_metadata.sparql
csvcubed/inspect/sparql_handler/sparql_queries/select_codelist_csv_url.sparql
csvcubed/inspect/sparql_handler/sparql_queries/select_codelist_primary_key_by_csv_url.sparql
csvcubed/inspect/sparql_handler/sparql_queries/select_codelists_and_cols.sparql
csvcubed/inspect/sparql_handler/sparql_queries/select_column_definitions.sparql
csvcubed/inspect/sparql_handler/sparql_queries/select_csvw_table_schema_file_dependencies.sparql
csvcubed/inspect/sparql_handler/sparql_queries/select_data_set_dsd_csv_url.sparql
csvcubed/inspect/sparql_handler/sparql_queries/select_dsd_qube_components.sparql
csvcubed-0.5.1.dist-info/LICENSE
csvcubed-0.5.1.dist-info/METADATA
csvcubed-0.5.1.dist-info/WHEEL
csvcubed-0.5.1.dist-info/entry_points.txt
csvcubed-0.5.1.dist-info/RECORD
