Metadata-Version: 2.1
Name: csvcubed
Version: 0.5.1
Summary: A tool to generate RDF Data Cube style CSV-W cubes from tidy CSV files. Part of the csvcubed family.
License: Apache-2.0
Author: Integrated Data Service - Dissemination
Author-email: csvcubed@gsscogs.uk
Requires-Python: >=3.9,<3.12
Classifier: License :: OSI Approved :: Apache Software License
Classifier: Programming Language :: Python :: 3
Classifier: Programming Language :: Python :: 3.9
Classifier: Programming Language :: Python :: 3.10
Classifier: Programming Language :: Python :: 3.11
Requires-Dist: click (>=8.0.0)
Requires-Dist: csvcubed-models (>=0.1.10,<0.2.0)
Requires-Dist: jsonschema (>=4.4.0,<=4.17.3)
Requires-Dist: numpy (<2.0.0)
Requires-Dist: pandas (>=1.3,<2.1.0)
Requires-Dist: platformdirs (>=3.5.0,<4.0.0)
Requires-Dist: python-dateutil (>=2.8.2,<3.0.0)
Requires-Dist: requests (>=2.27.1,<3.0.0)
Requires-Dist: requests-cache (>=0.9.3,<0.10.0)
Requires-Dist: setuptools (<70)
Requires-Dist: treelib (>=1.6.1,<2.0.0)
Requires-Dist: uritemplate (>=4.1.1,<5.0.0)
Requires-Dist: urllib3 (>=1.0.0,<2.0.0)
